MANIFEST.in
README.rst
setup.cfg
setup.py
toggl_dinero/__init__.py
toggl_dinero/cli.py
toggl_dinero/dinero.py
toggl_dinero/toggl.py
toggl_dinero/version.py
toggl_dinero.egg-info/PKG-INFO
toggl_dinero.egg-info/SOURCES.txt
toggl_dinero.egg-info/dependency_links.txt
toggl_dinero.egg-info/entry_points.txt
toggl_dinero.egg-info/requires.txt
toggl_dinero.egg-info/top_level.txt