Metadata-Version: 1.2
Name: toggl-dinero
Version: 0.2.1
Summary: Dinero invoicing from Toggl time entries.
Home-page: https://github.com/geanix/toggl-dinero
Author: Esben Haabendal
Author-email: esben@geanix.com
License: MIT
Download-URL: https://github.com/geanix/toggl-dinero/archive/0.2.1.tar.gz
Platform: UNKNOWN
Classifier: Development Status :: 3 - Alpha
Classifier: Intended Audience :: Developers
Classifier: Topic :: Software Development :: Libraries
Classifier: Topic :: Office/Business :: Financial
Classifier: Topic :: Office/Business :: Financial :: Accounting
Classifier: License :: OSI Approved :: MIT License
Classifier: Programming Language :: Python :: 3
Classifier: Programming Language :: Python :: 3.6
Classifier: Programming Language :: Python :: 3.7
Classifier: Programming Language :: Python :: 3.8
Classifier: Operating System :: OS Independent
Requires-Python: >=3
